s3_uploader/__init__.py
s3_uploader/client.py
s3_uploader/config.py
s3_uploader/uploader.py
s3_uploader/utils.py
fastapi_async_s3uploader-1.0.0.dist-info/METADATA
fastapi_async_s3uploader-1.0.0.dist-info/WHEEL
fastapi_async_s3uploader-1.0.0.dist-info/top_level.txt
fastapi_async_s3uploader-1.0.0.dist-info/RECORD
