Metadata-Version: 2.4
Name: fastapi-async-s3uploader
Version: 1.0.0
Summary: A reusable file uploader package for FastAPI and AWS S3
Author: Md Anisur Rahman
Requires-Dist: aioboto3>=10.4.0
Requires-Dist: fastapi>=0.95
Requires-Dist: pydantic>=1.10
Dynamic: author
Dynamic: requires-dist
Dynamic: summary
